{
  "tag_name": "progress",
  "struct_name": "Progress",
  "submodule_name": "forms",
  "mdn_link": "https://developer.mozilla.org/en-US/docs/Web/HTML/Element/progress",
  "has_global_attributes": true,
  "has_closing_tag": true,
  "attributes": [
    {
      "name": "value",
      "description": "Current value of the element",
      "field_name": "value",
      "ty": "String"
    },
    {
      "name": "max",
      "description": "Upper bound of range",
      "field_name": "max",
      "ty": "String"
    }
  ],
  "dom_interface": "HTMLProgressElement",
  "content_categories": [
    "Flow",
    "Phrasing",
    "Palpable"
  ],
  "permitted_content": [
    {
      "Category": "Phrasing"
    }
  ],
  "permitted_parents": [
    {
      "Category": "Flow"
    },
    {
      "Category": "Phrasing"
    }
  ]
}