{
  "tag_name": "embed",
  "struct_name": "Embed",
  "submodule_name": "embedded",
  "mdn_link": "https://developer.mozilla.org/en-US/docs/Web/HTML/Element/embed",
  "has_global_attributes": true,
  "has_closing_tag": false,
  "attributes": [
    {
      "name": "src",
      "description": "Address of the resource",
      "field_name": "src",
      "ty": "String"
    },
    {
      "name": "type",
      "description": "Type of embedded resource",
      "field_name": "type_",
      "ty": "String"
    },
    {
      "name": "width",
      "description": "Horizontal dimension",
      "field_name": "width",
      "ty": "String"
    },
    {
      "name": "height",
      "description": "Vertical dimension",
      "field_name": "height",
      "ty": "String"
    }
  ],
  "dom_interface": "HTMLEmbedElement",
  "content_categories": [
    "Flow",
    "Phrasing",
    "Embedded",
    "Interactive",
    "Palpable"
  ],
  "permitted_child_elements": [
    "Abbreviation",
    "Address",
    "Anchor",
    "Audio",
    "BidirectionalIsolate",
    "BidirectionalTextOverride",
    "BlockQuote",
    "Bold",
    "Button",
    "Canvas",
    "Cite",
    "Code",
    "Data",
    "DataList",
    "Definition",
    "DeletedText",
    "DescriptionList",
    "Details",
    "Dialog",
    "Division",
    "Embed",
    "Emphasis",
    "Fieldset",
    "Figure",
    "Footer",
    "Form",
    "Header",
    "Iframe",
    "Image",
    "ImageMap",
    "Input",
    "InsertedText",
    "Italic",
    "KeyboardInput",
    "Label",
    "LineBreak",
    "LineBreakOpportunity",
    "MarkText",
    "Menu",
    "Meter",
    "Object",
    "OrderedList",
    "Output",
    "Paragraph",
    "Picture",
    "PreformattedText",
    "Progress",
    "Quotation",
    "RubyAnnotation",
    "SampleOutput",
    "Script",
    "Select",
    "SideComment",
    "Slot",
    "Span",
    "StrikeThrough",
    "Strong",
    "SubScript",
    "SuperScript",
    "Table",
    "Template",
    "TextArea",
    "ThematicBreak",
    "Time",
    "Underline",
    "UnorderedList",
    "Variable",
    "Video"
  ]
}